py_raytrace/__init__.py
py_raytrace/objects.json
py_raytrace/py_raytrace.py
py_raytrace-0.5.2.dist-info/LICENCE
py_raytrace-0.5.2.dist-info/METADATA
py_raytrace-0.5.2.dist-info/WHEEL
py_raytrace-0.5.2.dist-info/entry_points.txt
py_raytrace-0.5.2.dist-info/top_level.txt
py_raytrace-0.5.2.dist-info/RECORD
