Metadata-Version: 2.1
Name: py-raytrace
Version: 0.5.2
Summary: A simple ray tracing application
Author: Pranav A.
Author-email: prnv.school@gmail.com
License: MIT
License-File: LICENCE
Requires-Dist: numpy
Requires-Dist: Pillow
Requires-Dist: tqdm
Requires-Dist: matplotlib
